README.md
setup.py
gb_automation_client.egg-info/PKG-INFO
gb_automation_client.egg-info/SOURCES.txt
gb_automation_client.egg-info/dependency_links.txt
gb_automation_client.egg-info/requires.txt
gb_automation_client.egg-info/top_level.txt
gba/__init__.py
gba/gba.py