Metadata-Version: 2.1
Name: gb-automation-client
Version: 0.0.2
Summary: Python GameBench Automation (GBA) client
Home-page: https://github.com/GameBench/gba-client-python
Author: Ade Slade
Author-email: ade@gamebench.net
License: UNKNOWN
Platform: UNKNOWN
Classifier: Programming Language :: Python :: 3
Classifier: License :: OSI Approved :: MIT License
Classifier: Operating System :: OS Independent
Requires-Python: >=3.6
